dataroot/__init__.py
dataroot/client.py
dataroot/consumer.py
dataroot/request.py
dataroot/utils.py
dataroot/version.py
dataroot/test/__init__.py
dataroot/test/client.py
dataroot/test/consumer.py
dataroot/test/module.py
dataroot/test/request.py
dataroot/test/utils.py
dataroot_python-1.0.0.dist-info/DESCRIPTION.rst
dataroot_python-1.0.0.dist-info/METADATA
dataroot_python-1.0.0.dist-info/RECORD
dataroot_python-1.0.0.dist-info/WHEEL
dataroot_python-1.0.0.dist-info/metadata.json
dataroot_python-1.0.0.dist-info/top_level.txt
