Metadata-Version: 2.0
Name: dataroot-python
Version: 1.0.0
Summary: The hassle-free way to integrate dataroot into any python application.
Home-page: https://github.com/dataroot/dataroot-python
Author: Dataroot
Author-email: ivan.didur@dataroot.co
License: MIT License
Platform: UNKNOWN
Classifier: Development Status :: 5 - Production/Stable
Classifier: Intended Audience :: Developers
Classifier: License :: OSI Approved :: MIT License
Classifier: Operating System :: OS Independent
Classifier: Programming Language :: Python
Classifier: Programming Language :: Python :: 2
Classifier: Programming Language :: Python :: 2.6
Classifier: Programming Language :: Python :: 2.7
Classifier: Programming Language :: Python :: 3
Classifier: Programming Language :: Python :: 3.2
Classifier: Programming Language :: Python :: 3.3
Classifier: Programming Language :: Python :: 3.4
Classifier: Programming Language :: Python :: 3.5
Requires-Dist: python-dateutil
Requires-Dist: requests
Requires-Dist: six
